<annotation>
	<folder>images</folder>
	<filename>fail_picture5_1756519660.png</filename>
	<path>D:\jumpjump\data\images\fail_picture5_1756519660.png</path>
	<source>
		<database>Unknown</database>
	</source>
	<size>
		<width>571</width>
		<height>1081</height>
		<depth>3</depth>
	</size>
	<segmented>0</segmented>
	<object>
		<name>piece</name>
		<pose>Unspecified</pose>
		<truncated>0</truncated>
		<difficult>0</difficult>
		<bndbox>
			<xmin>179</xmin>
			<ymin>544</ymin>
			<xmax>210</xmax>
			<ymax>650</ymax>
		</bndbox>
	</object>
	<object>
		<name>target</name>
		<pose>Unspecified</pose>
		<truncated>0</truncated>
		<difficult>0</difficult>
		<bndbox>
			<xmin>419</xmin>
			<ymin>451</ymin>
			<xmax>529</xmax>
			<ymax>514</ymax>
		</bndbox>
	</object>
</annotation>
