<annotation>
	<folder>images</folder>
	<filename>fail_picture6_1756568446.png</filename>
	<path>D:\jumpjump\data\images\fail_picture6_1756568446.png</path>
	<source>
		<database>Unknown</database>
	</source>
	<size>
		<width>571</width>
		<height>1081</height>
		<depth>3</depth>
	</size>
	<segmented>0</segmented>
	<object>
		<name>piece</name>
		<pose>Unspecified</pose>
		<truncated>0</truncated>
		<difficult>0</difficult>
		<bndbox>
			<xmin>355</xmin>
			<ymin>518</ymin>
			<xmax>386</xmax>
			<ymax>624</ymax>
		</bndbox>
	</object>
	<object>
		<name>target</name>
		<pose>Unspecified</pose>
		<truncated>0</truncated>
		<difficult>0</difficult>
		<bndbox>
			<xmin>111</xmin>
			<ymin>476</ymin>
			<xmax>352</xmax>
			<ymax>616</ymax>
		</bndbox>
	</object>
</annotation>
